priority_collections-0.0.3.dist-info/RECORD
priority_collections-0.0.3.dist-info/METADATA
priority_collections-0.0.3.dist-info/top_level.txt
priority_collections-0.0.3.dist-info/WHEEL
priority_collections/priority_heap.pyx
priority_collections/priority_heap.cpython-38-x86_64-linux-gnu.so
priority_collections/__init__.py
priority_collections/priority_heap.pxd
