Metadata-Version: 1.0
Name: priority_collections
Version: 0.0.3
Summary: NGV Architecture Cython Building Modules
Home-page: UNKNOWN
Author: Eleftherios Zisis
Author-email: eleftherios.zisis@epfl.ch
License: UNKNOWN
Platform: UNKNOWN
